[
  {
    "question": "Aggregate demand components",
    "answer": "C + I + G + NX"
  },
  {
    "question": "Phillips curve shows",
    "answer": "Inflation–unemployment tradeoff (short run)"
  },
  {
    "question": "Natural rate of unemployment",
    "answer": "Frictional + structural"
  },
  {
    "question": "Quantity theory of money",
    "answer": "MV = PY"
  },
  {
    "question": "Okun’s law links",
    "answer": "GDP growth and unemployment changes"
  },
  {
    "question": "Automatic stabilizers",
    "answer": "Taxes and transfers that vary with income"
  },
  {
    "question": "Crowding out occurs when",
    "answer": "Government borrowing raises interest rates"
  },
  {
    "question": "Fiscal multiplier effect",
    "answer": "Change in output due to change in spending/taxes"
  },
  {
    "question": "Taylor rule guides",
    "answer": "Central bank interest rate setting"
  },
  {
    "question": "Real interest rate approx",
    "answer": "Nominal − inflation"
  },
  {
    "question": "Exchange rate regimes",
    "answer": "Fixed, floating, managed float"
  },
  {
    "question": "Current account records",
    "answer": "Trade in goods/services, income, transfers"
  },
  {
    "question": "Budget deficit adds to",
    "answer": "Public debt"
  },
  {
    "question": "Stagflation is",
    "answer": "High inflation with stagnant output"
  },
  {
    "question": "Automatic vs discretionary policy",
    "answer": "Built-in vs enacted case-by-case"
  },
  {
    "question": "GDP deflator measures",
    "answer": "Price level of all domestically produced final goods"
  },
  {
    "question": "NAIRU refers to",
    "answer": "Non-accelerating inflation rate of unemployment"
  },
  {
    "question": "Liquidity trap conditions",
    "answer": "Near-zero rates, monetary policy less effective"
  },
  {
    "question": "Balance of payments identity",
    "answer": "Current + capital/financial = 0"
  },
  {
    "question": "Seigniorage is",
    "answer": "Revenue from money creation"
  }
]
